ulaval_notify/__init__.py
ulaval_notify/configuration.py
ulaval_notify/constants.py
ulaval_notify/main.py
ulaval_notify/options.py
ulaval_notify/utils.py
ulaval_notify/api/__init__.py
ulaval_notify/api/constants.py
ulaval_notify/api/login.py
ulaval_notify/api/notifications.py
ulaval_notify/api/session.py
ulaval_notify/resources/images/ulaval-logo.png
ulaval_notify-0.1.0.dist-info/DESCRIPTION.rst
ulaval_notify-0.1.0.dist-info/METADATA
ulaval_notify-0.1.0.dist-info/RECORD
ulaval_notify-0.1.0.dist-info/WHEEL
ulaval_notify-0.1.0.dist-info/entry_points.txt
ulaval_notify-0.1.0.dist-info/metadata.json
ulaval_notify-0.1.0.dist-info/top_level.txt
