Metadata-Version: 2.0
Name: ulaval-notify
Version: 0.1.0
Summary: Display monPortail notifications
Home-page: https://github.com/AntoineGagne/ulaval-notify
Author: Antoine Gagné
Author-email: antoine.gagne.2@ulaval.ca
License: MIT
Keywords: notifications
Platform: any
Classifier: Programming Language :: Python :: 3
Classifier: Programming Language :: Python :: 3.6
Classifier: Operating System :: Unix
Classifier: Operating System :: MacOS :: MacOS X
Classifier: Operating System :: Microsoft :: Windows
Requires-Python: >=3
Requires-Dist: requests (>=2.18.4)
Requires-Dist: notify2 (>=0.3.1); sys_platform == "linux"
Requires-Dist: dbus-python (>=1.2.4); sys_platform == "linux"
Provides-Extra: daemon
Requires-Dist: python-daemon (>=2.1.2); extra == 'daemon'
Provides-Extra: dev
Requires-Dist: flake8; extra == 'dev'
Requires-Dist: pylint; extra == 'dev'
Requires-Dist: Sphinx; extra == 'dev'
